{
  "$schema": "https://developer.microsoft.com/json-schemas/fabric/item/report/definition/visualContainer/2.3.0/schema.json",
  "name": "9fe127ee4c734b576dc0",
  "position": {
    "x": 32,
    "y": 32,
    "z": 3000,
    "height": 304,
    "width": 432,
    "tabOrder": 2000
  },
  "visual": {
    "visualType": "clusteredBarChart",
    "query": {
      "queryState": {
        "Category": {
          "projections": [
            {
              "field": {
                "Column": {
                  "Expression": {
                    "SourceRef": {
                      "Entity": "FishTypesCFValues"
                    }
                  },
                  "Property": "SACN_Desc"
                }
              },
              "queryRef": "FishTypesCFValues.SACN_Desc",
              "nativeQueryRef": "SACN_Desc",
              "active": true
            }
          ]
        },
        "Y": {
          "projections": [
            {
              "field": {
                "Aggregation": {
                  "Expression": {
                    "Column": {
                      "Expression": {
                        "SourceRef": {
                          "Entity": "SeafoodData"
                        }
                      },
                      "Property": "UKConsumption"
                    }
                  },
                  "Function": 0
                }
              },
              "queryRef": "Sum(UKSeafoodSupplyChain.Consumption)",
              "nativeQueryRef": "Consumption",
              "displayName": "Consumption"
            },
            {
              "field": {
                "Aggregation": {
                  "Expression": {
                    "Column": {
                      "Expression": {
                        "SourceRef": {
                          "Entity": "SeafoodData"
                        }
                      },
                      "Property": "AllProduction"
                    }
                  },
                  "Function": 0
                }
              },
              "queryRef": "Sum(UKSeafoodSupplyChain.AllProduction)",
              "nativeQueryRef": "Production",
              "displayName": "Production"
            }
          ]
        }
      },
      "sortDefinition": {
        "sort": [
          {
            "field": {
              "Column": {
                "Expression": {
                  "SourceRef": {
                    "Entity": "FishTypesCFValues"
                  }
                },
                "Property": "SACN_Desc"
              }
            },
            "direction": "Ascending"
          }
        ]
      }
    },
    "objects": {
      "categoryAxis": [
        {
          "properties": {
            "showAxisTitle": {
              "expr": {
                "Literal": {
                  "Value": "false"
                }
              }
            }
          }
        }
      ],
      "valueAxis": [
        {
          "properties": {
            "show": {
              "expr": {
                "Literal": {
                  "Value": "true"
                }
              }
            },
            "showAxisTitle": {
              "expr": {
                "Literal": {
                  "Value": "false"
                }
              }
            },
            "labelDisplayUnits": {
              "expr": {
                "Literal": {
                  "Value": "1000000000D"
                }
              }
            }
          }
        }
      ]
    },
    "visualContainerObjects": {
      "title": [
        {
          "properties": {
            "text": {
              "expr": {
                "Literal": {
                  "Value": "'Lean fish consumption is double the production total'"
                }
              }
            }
          }
        }
      ],
      "border": [
        {
          "properties": {
            "show": {
              "expr": {
                "Literal": {
                  "Value": "true"
                }
              }
            },
            "color": {
              "solid": {
                "color": {
                  "expr": {
                    "Literal": {
                      "Value": "'#FFFFFF'"
                    }
                  }
                }
              }
            },
            "radius": {
              "expr": {
                "Literal": {
                  "Value": "30D"
                }
              }
            }
          }
        }
      ],
      "visualTooltip": [
        {
          "properties": {
            "show": {
              "expr": {
                "Literal": {
                  "Value": "false"
                }
              }
            }
          }
        }
      ]
    },
    "drillFilterOtherVisuals": true
  }
}